nekosama/__init__.py
nekosama/__main__.py
nekosama/consts.py
nekosama/core.py
nekosama/objects/anime.py
nekosama/objects/database.py
nekosama/objects/episode.py
nekosama-4.1.dist-info/LICENSE
nekosama-4.1.dist-info/METADATA
nekosama-4.1.dist-info/WHEEL
nekosama-4.1.dist-info/top_level.txt
nekosama-4.1.dist-info/RECORD
