Metadata-Version: 2.1
Name: nekosama
Version: 4.1
Summary: API Wrapper for neko-sama.fr
Author-email: Egsagon <egsagon12@gmail.com>
License: MIT License
Project-URL: Repository, https://github.com/Egsagon/nekosama
Keywords: nekosama,anime,downloader,french
Classifier: Development Status :: 5 - Production/Stable
Classifier: Programming Language :: Python
Requires-Python: >=3.11
License-File: LICENSE
Requires-Dist: httpx
Requires-Dist: yt-dlp
Requires-Dist: rich[progress]
